Metadata-Version: 2.1
Name: nmpyc
Version: 1.0.3
Summary: Python library for solving optimal control problems via model predictive control
Home-page: https://nmpyc.readthedocs.io/
Author: Jonas Schießl, Lisa Krügel
Author-email: nmpyc@uni-bayreuth.de
License: GNU Lesser General Public License version 3
Platform: UNKNOWN
License-File: LICENSE
